setup.py
lottanzb/__init__.py
lottanzb/backend.py
lottanzb/firstrun.py
lottanzb/gui.py
lottanzb/lottanzb.py
lottanzb/paths.py
lottanzb/prefs.py
lottanzb/prefsgui.py
lottanzb/util.py
lottanzb.egg-info/PKG-INFO
lottanzb.egg-info/SOURCES.txt
lottanzb.egg-info/dependency_links.txt
lottanzb.egg-info/entry_points.txt
lottanzb.egg-info/not-zip-safe
lottanzb.egg-info/top_level.txt