Metadata-Version: 1.0
Name: lottanzb
Version: 0.0.3.012
Summary: LottaNZB, the GTK HellaNZB front-end
Home-page: http://www.lottanzb.org/
Author: aVirulence
Author-email: avirulence@lottanzb.org
License: GPL
Platform: UNKNOWN
